Metadata-Version: 1.1
Name: unittest-dataprovider
Version: 1.0.3
Summary: PHPUnit-like @dataprovider decorator for unittest
Home-page: http://github.com/l-vo/unittest-data-provider
Author: drm from melp.nl, packaged for reuse by James Pic
Author-email: jamespic@gmail.com
License: MIT
Keywords: unittest dataprovider
Platform: UNKNOWN
Classifier: Development Status :: 3 - Alpha
Classifier: Intended Audience :: Developers
Classifier: License :: OSI Approved :: MIT License
Classifier: Operating System :: OS Independent
Classifier: Programming Language :: Python
Classifier: Programming Language :: Python :: 2
Classifier: Topic :: Software Development :: Libraries :: Python Modules
